gplay_devices.py
setup.py
gplay_devices.egg-info/PKG-INFO
gplay_devices.egg-info/SOURCES.txt
gplay_devices.egg-info/dependency_links.txt
gplay_devices.egg-info/top_level.txt