Metadata-Version: 1.0
Name: gplay-devices
Version: 0.1.1
Summary: List of supported devices on Google Play
Home-page: https://github.com/EncircleInc/gplay-devices
Author: Ronuk Raval
Author-email: ronuk.raval@gmail.com
License: MIT
Keywords: google-play supported-devices
Platform: UNKNOWN
